{
  "required": true,
  "package": "net.pythonbear.tead.mixin",
  "compatibilityLevel": "JAVA_17",
  "client": [
    "HeldItemRendererMixin",
    "ItemRendererAccessor",
    "ItemRendererMixin",
    "ModelLoaderMixin",
    "PlayerEntityRendererMixin"
  ],
  "injectors": {
    "defaultRequire": 1
  },
  "mixins": [
    "AbstractSkeletonEntityInitEquipmentMixin",
    "DrownedInitEquipmentMixin",
    "FireTrailMixin",
    "PiglinInitEquipmentMixin",
    "SmithingScreenHandlerMixin",
    "SwordItemMixin",
    "VindicatorInitEquipmentMixin",
    "WitherSkeletonInitEquipmentMixin",
    "ZombieInitEquipmentMixin",
    "ZombiePiglinInitEquipmentMixin"
  ]
}